pyplatex/__init__.py
pyplatex/detection/__init__.py
pyplatex/detection/yolo.py
pyplatex/examples/__init__.py
pyplatex/models/__init__.py
pyplatex/models/base_model.py
pyplatex/models/plate-detection-models/plate_detector_model_1.pt
pyplatex/ocr/__init__.py
pyplatex/ocr/main.py
pyplatex/postprocessing/__init__.py
pyplatex/preprocessing/__init__.py
pyplatex/utils/__init__.py
pyplatex-0.0.5.dist-info/LICENSE
pyplatex-0.0.5.dist-info/METADATA
pyplatex-0.0.5.dist-info/WHEEL
pyplatex-0.0.5.dist-info/top_level.txt
pyplatex-0.0.5.dist-info/RECORD
