Metadata-Version: 2.1
Name: pyplatex
Version: 0.0.5
Summary: A high-performance, scalable, and ready-to-use Automatic Number Plate Recognition (ANPR) package.
Home-page: https://github.com/nuhmanpk/pyplatex
Author: Nuhman Pk
Author-email: nuhmanpk7@gmail.com
License: MIT
Project-URL: Documentation, https://github.com/nuhmanpk/pyplatex/blob/main/README.md
Project-URL: Funding, https://github.com/sponsors/nuhmanpk
Project-URL: Source, https://github.com/nuhmanpk/pyplatex/
Project-URL: Tracker, https://github.com/nuhmanpk/pyplatex/issues
Platform: UNKNOWN
Classifier: Programming Language :: Python :: 3.9
Classifier: License :: OSI Approved :: MIT License
Classifier: Operating System :: OS Independent
Requires-Python: >=3.9
License-File: LICENSE
Requires-Dist: cv2filters==0.2.6
Requires-Dist: loguru==0.7.2
Requires-Dist: python-doctr==0.9.0
Requires-Dist: ultralytics==8.2.55
